[
  {
    "fromDate": "09/01/2024",
    "toDate": null,
    "time": null,
    "title": "Tuition Payment Due",
    "description": "The due date for the tuition payment for the upcoming school term."
  },
  {
    "fromDate": "09/07/2024",
    "toDate": null,
    "time": "9am-12pm",
    "title": "Social Work Day",
    "description": "Our mandatory social work event for adult family members. As a cooperative school, many hands make light work and that includes getting the school in tip top shape for the year. Please send an adult to help get the school ready (infants in carriers or strollers welcome!). We will have a variety of cleaning and maintenance tasks to take care of."
  },
  {
    "fromDate": "09/09/2024",
    "toDate": null,
    "time": "9am-9:30am or 9:30am-10am",
    "title": "Big Nursery: 3 & 5 Day Orientation",
    "description": "Orientation session for children enrolled in the 3 and 5-day programs at Big Nursery."
  },
  {
    "fromDate": "09/10/2024",
    "toDate": null,
    "time": "9am-9:30am or 9:30am-10am",
    "title": "Big Nursery: 2 Day Orientation",
    "description": "Orientation session for children enrolled in the 2-day program at Big Nursery."
  },
  {
    "fromDate": "09/11/2024",
    "toDate": null,
    "time": "9am-10:30am",
    "title": "Big Nursery: 3 & 5 Day Parent Meeting & Short Day",
    "description": "Parent meeting followed by a short day session for children in the 3 and 5-day programs at Big Nursery."
  },
  {
    "fromDate": "09/12/2024",
    "toDate": null,
    "time": "9am-10:30am",
    "title": "Big Nursery: 2 Day Parent Meeting & Short Day",
    "description": "Parent meeting followed by a short day session for children in the 2-day program at Big Nursery."
  },
  {
    "fromDate": "09/13/2024",
    "toDate": null,
    "time": "9am-12pm",
    "title": "Big Nursery: 3 & 5 Day First Full Day",
    "description": "The first full day of school for children in the 3 and 5-day programs at Big Nursery."
  },
  {
    "fromDate": "09/16/2024",
    "toDate": null,
    "time": "9am-9:30am",
    "title": "Young Nursery: M/Tu Orientation",
    "description": "Orientation session for children attending Young Nursery on Mondays and Tuesdays."
  },
  {
    "fromDate": "09/17/2024",
    "toDate": null,
    "time": "9am-10:30am",
    "title": "Young Nursery: M/Tu Parent Meeting & Short Day",
    "description": "Parent meeting followed by a short day session for children in the Monday/Tuesday Young Nursery program."
  },
  {
    "fromDate": "09/17/2024",
    "toDate": null,
    "time": "9am-12pm",
    "title": "Big Nursery: 2 Day First Full Day",
    "description": "The first full day of school for children in the 2-day program at Big Nursery."
  },
  {
    "fromDate": "09/19/2024",
    "toDate": null,
    "time": "9am-10:30am",
    "title": "Young Nursery: W/Th Parent Meeting & Short Day",
    "description": "Parent meeting followed by a short day session for children in the Wednesday/Thursday Young Nursery program."
  },
  {
    "fromDate": "09/23/2024",
    "toDate": null,
    "time": "9am-11am",
    "title": "Young Nursery: M/Tu Short Day",
    "description": "Short day session for children in the Monday/Tuesday Young Nursery program."
  },
  {
    "fromDate": "09/24/2024",
    "toDate": null,
    "time": "9am-11am",
    "title": "Young Nursery: M/Tu Short Day",
    "description": "Short day session for children in the Monday/Tuesday Young Nursery program."
  },
  {
    "fromDate": "09/25/2024",
    "toDate": null,
    "time": "9am-11am",
    "title": "Young Nursery: W/Th Short Day",
    "description": "Short day session for children in the Wednesday/Thursday Young Nursery program."
  },
  {
    "fromDate": "09/26/2024",
    "toDate": null,
    "time": "9am-11am",
    "title": "Young Nursery: W/Th Short Day",
    "description": "Short day session for children in the Wednesday/Thursday Young Nursery program."
  },
  {
    "fromDate": "09/30/2024",
    "toDate": null,
    "time": "9am-11:30am",
    "title": "Young Nursery: M/Tu First Full Day",
    "description": "The first full day of school for children in the Monday/Tuesday Young Nursery program."
  },
  {
    "fromDate": "10/02/2024",
    "toDate": null,
    "time": "9am-11:30am",
    "title": "Young Nursery: W/Th First Full Day",
    "description": "The first full day of school for children in the Wednesday/Thursday Young Nursery program."
  },
  {
    "fromDate": "10/09/2024",
    "toDate": null,
    "time": "7:45pm-8:30pm",
    "title": "Officer's Meeting",
    "description": "Meeting for the school's officers to discuss organizational matters."
  },
  {
    "fromDate": "10/14/2024",
    "toDate": null,
    "time": null,
    "title": "No School - Indigenous People's Day",
    "description": "School closed in observance of Indigenous People's Day."
  },
  {
    "fromDate": "10/22/2024",
    "toDate": "10/23/2024",
    "time": null,
    "title": "Picture Day",
    "description": "Don't forget to dress your best for picture day! Photos will be taken throughout the school day."
  },
  {
    "fromDate": "10/29/2024",
    "toDate": "10/30/2024",
    "time": null,
    "title": "Picture Day - Makeup Date",
    "description": "If a student missed picture day, the makeup session will be held during the school day."
  },
  {
    "fromDate": "11/01/2024",
    "toDate": null,
    "time": null,
    "title": "Tuition Payment Due",
    "description": "The due date for the next tuition payment."
  },
  {
    "fromDate": "11/11/2024",
    "toDate": null,
    "time": null,
    "title": "No School - Veteran's Day",
    "description": "School closed in observance of Veteran's Day."
  },
  {
    "fromDate": "11/13/2024",
    "toDate": null,
    "time": "7pm-8:30pm",
    "title": "Full Board Meeting",
    "description": "A meeting of the full board; all members of the school community are welcome to attend."
  },
  {
    "fromDate": "11/13/2024",
    "toDate": null,
    "time": null,
    "title": "Fundraising - Pie Pickup Day",
    "description": "Day for picking up pies ordered as part of the school's fundraising activities."
  },
  {
    "fromDate": "11/27/2024",
    "toDate": "11/30/2024",
    "time": null,
    "title": "No School - Thanksgiving Recess",
    "description": "School closed for the Thanksgiving holiday break."
  },
  {
    "fromDate": "12/02/2024",
    "toDate": null,
    "time": null,
    "title": "No School - Teacher Work Day",
    "description": "A work day for teachers; no classes will be held for students."
  },
  {
    "fromDate": "12/03/2024",
    "toDate": null,
    "time": null,
    "title": "Big Nursery: 2 & 5 Day New Rooms",
    "description": ""
  },
  {
    "fromDate": "12/04/2024",
    "toDate": null,
    "time": null,
    "title": "Big Nursery: 3 Day New Rooms",
    "description": ""
  },
  {
    "fromDate": "12/11/2024",
    "toDate": null,
    "time": "7pm-8:30pm",
    "title": "Officer's Meeting",
    "description": "Meeting for the school's officers; all are welcome to attend."
  },
  {
    "fromDate": "12/23/2024",
    "toDate": "01/03/2025",
    "time": null,
    "title": "No School - Winter Recess",
    "description": "School closed for the winter holiday break."
  },
  {
    "fromDate": "01/08/2025",
    "toDate": null,
    "time": "7pm-8:30pm",
    "title": "Full Board Meeting",
    "description": "A meeting of the full board; all members of the school community are welcome to attend."
  },
  {
    "fromDate": "01/11/2025",
    "toDate": null,
    "time": "Time TBD",
    "title": "Public Open House",
    "description": "Tentative date for the school's public open house event. Time to be determined."
  },
  {
    "fromDate": "01/14/2025",
    "toDate": null,
    "time": null,
    "title": "Young Nursery: M/Tu No School - Parent Teacher Conferences",
    "description": "No school for children in the Monday/Tuesday Young Nursery program due to parent-teacher conferences."
  },
  {
    "fromDate": "01/16/2025",
    "toDate": null,
    "time": "7pm-8:30pm",
    "title": "Young Nursery: W/Th and Big Nursery - No School - Parent Teacher Conferences",
    "description": "No school for children in the Wednesday/Thursday Young Nursery and Big Nursery programs due to parent-teacher conferences."
  },
  {
    "fromDate": "01/17/2025",
    "toDate": null,
    "time": null,
    "title": "Big Nursery: No School - Parent Teacher Conferences",
    "description": "No school for Big Nursery students due to parent-teacher conferences."
  },
  {
    "fromDate": "01/20/2025",
    "toDate": null,
    "time": null,
    "title": "No School - MLK Jr. Day",
    "description": "School closed in observance of Martin Luther King Jr. Day."
  },
  {
    "fromDate": "01/27/2025",
    "toDate": null,
    "time": null,
    "title": "Registration Opens 2025-2026 [Current Families]",
    "description": "Registration opens for current families for the 2025-2026 school year."
  },
  {
    "fromDate": "02/03/2025",
    "toDate": null,
    "time": null,
    "title": "Registration Opens 2025-2026 [Alumni]",
    "description": "Registration opens for alumni families for the 2025-2026 school year."
  },
  {
    "fromDate": "02/10/2025",
    "toDate": null,
    "time": null,
    "title": "Registration Opens 2025-2026 [Public]",
    "description": "Registration opens to the public for the 2025-2026 school year."
  },
  {
    "fromDate": "02/12/2025",
    "toDate": null,
    "time": "7pm",
    "title": "Officer's Meeting",
    "description": "Meeting for the school's officers; all are welcome to attend."
  },
  {
    "fromDate": "02/17/2025",
    "toDate": "02/21/2025",
    "time": null,
    "title": "No School - February Recess",
    "description": "School closed for the February recess break."
  },
  {
    "fromDate": "03/03/2025",
    "toDate": null,
    "time": null,
    "title": "Summer Camp 2025 Registration Opens",
    "description": "Registration opens for the Summer Camp 2025 program."
  },
  {
    "fromDate": "03/10/2025",
    "toDate": null,
    "time": null,
    "title": "No School - Teacher Work Day",
    "description": "Teacher work day; no classes for students."
  },
  {
    "fromDate": "03/11/2025",
    "toDate": null,
    "time": null,
    "title": "Big Nursery: New Rooms for 2 & 5 Day",
    "description": ""
  },
  {
    "fromDate": "03/12/2025",
    "toDate": null,
    "time": null,
    "title": "Big Nursery: New Rooms for 3 Day",
    "description": ""
  },
  {
    "fromDate": "03/12/2025",
    "toDate": null,
    "time": "7pm-8:30pm",
    "title": "Full Board Meeting",
    "description": "A meeting of the full board; all members of the school community are welcome to attend."
  },
  {
    "fromDate": "04/01/2025",
    "toDate": null,
    "time": null,
    "title": "Tuition Deposit Due for 2025-2026",
    "description": "The deposit for tuition for the 2025-2026 school year is due."
  },
  {
    "fromDate": "04/09/2025",
    "toDate": null,
    "time": "7pm-8:30pm",
    "title": "Officer's Meeting",
    "description": "Meeting for the school's officers; all are welcome to attend."
  },
  {
    "fromDate": "04/14/2025",
    "toDate": "04/18/2025",
    "time": null,
    "title": "No School - Spring Recess",
    "description": "School closed for the spring recess break."
  },
  {
    "fromDate": "05/14/2025",
    "toDate": null,
    "time": "7pm-8:30pm",
    "title": "Full Board Meeting",
    "description": "A meeting of the full board; all members of the school community are welcome to attend."
  },
  {
    "fromDate": "05/20/2025",
    "toDate": null,
    "time": null,
    "title": "Young Nursery: M/Tu Last Day Picnic",
    "description": "End-of-year picnic for children in the Monday/Tuesday Young Nursery program."
  },
  {
    "fromDate": "05/22/2025",
    "toDate": null,
    "time": null,
    "title": "Young Nursery: W/Th Last Day Picnic",
    "description": "End-of-year picnic for children in the Wednesday/Thursday Young Nursery program."
  },
  {
    "fromDate": "05/26/2025",
    "toDate": null,
    "time": null,
    "title": "No School - Memorial Day",
    "description": "School closed in observance of Memorial Day."
  },
  {
    "fromDate": "06/01/2025",
    "toDate": null,
    "time": null,
    "title": "Tuition Payment Due for 2025-2026",
    "description": "The due date for the first tuition payment for the 2025-2026 school year."
  },
  {
    "fromDate": "06/03/2025",
    "toDate": null,
    "time": null,
    "title": "Big Nursery: 2 Day Last Day & Picnic",
    "description": "Last day of school and picnic for children in the 2-day program at Big Nursery."
  },
  {
    "fromDate": "06/04/2025",
    "toDate": null,
    "time": null,
    "title": "Big Nursery: 3 & 5 Day Last Day & Picnic",
    "description": "Last day of school and picnic for children in the 3 and 5-day programs at Big Nursery."
  },
  {
    "fromDate": "06/09/2025",
    "toDate": "06/11/2025",
    "time": null,
    "title": "Summer Camp Week 1",
    "description": "The first week of the school's Summer Camp program."
  },
  {
    "fromDate": "06/12/2025",
    "toDate": null,
    "time": null,
    "title": "No School - Summer Recess",
    "description": "School closed for summer recess."
  },
  {
    "fromDate": "06/16/2025",
    "toDate": "06/19/2025",
    "time": null,
    "title": "Summer Camp Week 2",
    "description": "The second week of the school's Summer Camp program."
  },
  {
    "fromDate": "06/20/2025",
    "toDate": "09/07/2025",
    "time": null,
    "title": "No School - Summer Recess",
    "description": "School closed for summer recess."
  }
]
